uniezgame.cp313-win_amd64.pyd
uniezgame/SDL2.dll
uniezgame/__init__.py
uniezgame/mylib.cpp
uniezgame/uniezgame.cp313-win_amd64.pyd
uniezgame/uniezgame.dll
uniezgame-0.4.6.dist-info/METADATA
uniezgame-0.4.6.dist-info/WHEEL
uniezgame-0.4.6.dist-info/top_level.txt
uniezgame-0.4.6.dist-info/RECORD
