Metadata-Version: 2.1
Name: uniezgame
Version: 0.4.6
Summary: Uniezgame - Python C++ bindings using pybind11
Home-page: https://github.com/slawek1q2w3e4r/uniezgame
Author: Michał Lewandowski
Author-email: michal.lewandowski.113@gmail.com
License: MIT
Classifier: Programming Language :: Python :: 3
Classifier: License :: OSI Approved :: MIT License
Classifier: Operating System :: OS Independent
Requires-Python: >=3.6
